{
	"forge_marker": 1,
	"defaults": {
  		"custom": { "flip-v": true },
		"model": "miniaturia_mod:mt_object_armor_head.obj"
	},

    "variants": {

    	"click": {
	    		"0": {
					"textures": {
						"#m_0": "miniaturia_mod:blocks/leaves_palm",
						"#m_1": "miniaturia_mod:blocks/log_jungle",
						"particle": "miniaturia_mod:blocks/leaves_palm"
			 		}
			 	},
			 	"1": {
					"textures": {
						"#m_0": "miniaturia_mod:blocks/leaves_palm_b",
						"#m_1": "miniaturia_mod:blocks/log_jungle",
						"particle": "miniaturia_mod:blocks/leaves_palm_b"
			 		}
	    		},
	    		"2": {
					"textures": {
						"#m_0": "miniaturia_mod:blocks/leaves_cycad_0",
						"#m_1": "miniaturia_mod:blocks/leaves_cycad_1",
						"particle": "miniaturia_mod:blocks/leaves_cycad_1"
			 		}
	    		},
	    		"3": {
					"textures": {
						"#m_0": "miniaturia_mod:blocks/leaves_cycad_b_0",
						"#m_1": "miniaturia_mod:blocks/leaves_cycad_b_1",
						"particle": "miniaturia_mod:blocks/leaves_cycad_b_1"
			 		}
	    		}
	    },

    	"facing": {
    		"north":	{ "y": 0 },
    		"east":		{ "y": 90 },
    		"south":	{ "y": 180 },
    		"west":		{ "y": 270 }
		},

    	"shape": {
    		"bottom":	{ "model": "miniaturia_mod:mt_palm_lower.obj" },
    		"middle":	{ "model": "miniaturia_mod:mt_palm_lower.obj" },
    		"top":		{ "model": "miniaturia_mod:mt_palm_upper.obj" },
    		"single":	{ "model": "miniaturia_mod:mt_palm_upper.obj" }
		},

		"click=0,facing=north,shape=bottom":	[{}],
		"click=0,facing=east,shape=bottom":		[{}],
		"click=0,facing=south,shape=bottom":	[{}],
		"click=0,facing=west,shape=bottom":		[{}],

		"click=0,facing=north,shape=middle":	[{}],
		"click=0,facing=east,shape=middle":		[{}],
		"click=0,facing=south,shape=middle":	[{}],
		"click=0,facing=west,shape=middle":		[{}],

		"click=0,facing=north,shape=top":		[{}],
		"click=0,facing=east,shape=top":		[{}],
		"click=0,facing=south,shape=top":		[{}],
		"click=0,facing=west,shape=top":		[{}],

		"click=0,facing=north,shape=single":	[{}],
		"click=0,facing=east,shape=single":		[{}],
		"click=0,facing=south,shape=single":	[{}],
		"click=0,facing=west,shape=single":		[{}],

		"click=1,facing=north,shape=bottom":	[{}],
		"click=1,facing=east,shape=bottom":		[{}],
		"click=1,facing=south,shape=bottom":	[{}],
		"click=1,facing=west,shape=bottom":		[{}],

		"click=1,facing=north,shape=middle":	[{}],
		"click=1,facing=east,shape=middle":		[{}],
		"click=1,facing=south,shape=middle":	[{}],
		"click=1,facing=west,shape=middle":		[{}],

		"click=1,facing=north,shape=top":		[{}],
		"click=1,facing=east,shape=top":		[{}],
		"click=1,facing=south,shape=top":		[{}],
		"click=1,facing=west,shape=top":		[{}],

		"click=1,facing=north,shape=single":	[{}],
		"click=1,facing=east,shape=single":		[{}],
		"click=1,facing=south,shape=single":	[{}],
		"click=1,facing=west,shape=single":		[{}],

		"click=2,facing=north,shape=bottom":	{ "model": "miniaturia_mod:mt_cycad_upper.obj", "y": 90 },
		"click=2,facing=east,shape=bottom":		{ "model": "miniaturia_mod:mt_cycad_upper.obj", "y": 180 },
		"click=2,facing=south,shape=bottom":	{ "model": "miniaturia_mod:mt_cycad_upper.obj", "y": 270 },
		"click=2,facing=west,shape=bottom":		{ "model": "miniaturia_mod:mt_cycad_upper.obj" },

		"click=2,facing=north,shape=middle":	{ "model": "miniaturia_mod:mt_cycad_upper.obj", "y": 270 },
		"click=2,facing=east,shape=middle":		{ "model": "miniaturia_mod:mt_cycad_upper.obj" },
		"click=2,facing=south,shape=middle":	{ "model": "miniaturia_mod:mt_cycad_upper.obj", "y": 90 },
		"click=2,facing=west,shape=middle":		{ "model": "miniaturia_mod:mt_cycad_upper.obj", "y": 180 },

		"click=2,facing=north,shape=top":		{ "model": "miniaturia_mod:mt_cycad_upper.obj" },
		"click=2,facing=east,shape=top":		{ "model": "miniaturia_mod:mt_cycad_upper.obj" },
		"click=2,facing=south,shape=top":		{ "model": "miniaturia_mod:mt_cycad_upper.obj" },
		"click=2,facing=west,shape=top":		{ "model": "miniaturia_mod:mt_cycad_upper.obj" },

		"click=2,facing=north,shape=single":	{ "model": "miniaturia_mod:mt_cycad_upper.obj" },
		"click=2,facing=east,shape=single":		{ "model": "miniaturia_mod:mt_cycad_upper.obj" },
		"click=2,facing=south,shape=single":	{ "model": "miniaturia_mod:mt_cycad_upper.obj" },
		"click=2,facing=west,shape=single":		{ "model": "miniaturia_mod:mt_cycad_upper.obj" },


		"click=3,facing=north,shape=bottom":	{ "model": "miniaturia_mod:mt_cycad_upper.obj", "y": 90 },
		"click=3,facing=east,shape=bottom":		{ "model": "miniaturia_mod:mt_cycad_upper.obj", "y": 180 },
		"click=3,facing=south,shape=bottom":	{ "model": "miniaturia_mod:mt_cycad_upper.obj", "y": 270 },
		"click=3,facing=west,shape=bottom":		{ "model": "miniaturia_mod:mt_cycad_upper.obj" },

		"click=3,facing=north,shape=middle":	{ "model": "miniaturia_mod:mt_cycad_upper.obj", "y": 270 },
		"click=3,facing=east,shape=middle":		{ "model": "miniaturia_mod:mt_cycad_upper.obj" },
		"click=3,facing=south,shape=middle":	{ "model": "miniaturia_mod:mt_cycad_upper.obj", "y": 90 },
		"click=3,facing=west,shape=middle":		{ "model": "miniaturia_mod:mt_cycad_upper.obj", "y": 180 },

		"click=3,facing=north,shape=top":		{ "model": "miniaturia_mod:mt_cycad_upper.obj" },
		"click=3,facing=east,shape=top":		{ "model": "miniaturia_mod:mt_cycad_upper.obj" },
		"click=3,facing=south,shape=top":		{ "model": "miniaturia_mod:mt_cycad_upper.obj" },
		"click=3,facing=west,shape=top":		{ "model": "miniaturia_mod:mt_cycad_upper.obj" },

		"click=3,facing=north,shape=single":	{ "model": "miniaturia_mod:mt_cycad_upper.obj" },
		"click=3,facing=east,shape=single":		{ "model": "miniaturia_mod:mt_cycad_upper.obj" },
		"click=3,facing=south,shape=single":	{ "model": "miniaturia_mod:mt_cycad_upper.obj" },
		"click=3,facing=west,shape=single":		{ "model": "miniaturia_mod:mt_cycad_upper.obj" }
    }
}